orbitalfetch/__init__.py
orbitalfetch/orbital_fetch.py
orbitalfetch-1.0.3.dist-info/LICENSE
orbitalfetch-1.0.3.dist-info/METADATA
orbitalfetch-1.0.3.dist-info/WHEEL
orbitalfetch-1.0.3.dist-info/top_level.txt
orbitalfetch-1.0.3.dist-info/RECORD
