Metadata-Version: 2.1
Name: orbitalfetch
Version: 1.0.3
Summary: A Python library for downloading high-resolution satellite imagery from Google or ESRI.
Author: Hakimali
Author-email: datardihakim440@gmail.com
Classifier: Programming Language :: Python :: 3
Classifier: License :: OSI Approved :: MIT License
Classifier: Operating System :: OS Independent
Requires-Python: >=3.6
License-File: LICENSE
Requires-Dist: numpy
Requires-Dist: requests
Requires-Dist: rasterio
Requires-Dist: pillow
Requires-Dist: mercantile
